{"lessonCompleted": {"overall": 28.0, "change": null}, "speakingUsage": {"overall": 0.0, "change": null}, "coinsWords": {"overall": 66968.0, "change": null}, "lessonShared": {"overall": 1168.0, "change": null}, "translationsShared": {"overall": 12792.0, "change": null}, "lessonPublished": {"overall": 184.0, "change": null}, "lessonTaken": {"overall": 745.0, "change": null}, "translationsCreated": {"overall": 24230.0, "change": null}, "learnedWords": {"overall": 13951.0, "change": null}, "readingUsage": {"overall": 1991832.191, "change": null}, "listening": {"overall": 324.097639497987, "change": null}, "lessonImported": {"overall": 615.0, "change": null}, "coinsRead": {"overall": 124192.950559502, "change": null}, "reviewUsage": {"overall": 259414.237, "change": null}, "writing": {"overall": 2455.0, "change": null}, "createdLingQs": {"overall": 24405.0, "change": null}, "knownWords": {"overall": 11843.0, "change": null}, "listeningUsage": {"overall": 365637.681, "change": null}, "translationsUsed": {"overall": 32656.0, "change": null}, "reading": {"overall": 1450666.50561771, "change": null}, "coinsListen": {"overall": 11363.5961428425, "change": null}, "speaking": {"overall": 0.5, "change": null}}