{"lessonCompleted": {"overall": 28.0, "change": null}, "speakingUsage": {"overall": 0.0, "change": null}, "coinsWords": {"overall": 66217.0, "change": null}, "lessonShared": {"overall": 985.0, "change": null}, "translationsShared": {"overall": 12330.0, "change": null}, "lessonPublished": {"overall": 177.0, "change": null}, "lessonTaken": {"overall": 711.0, "change": null}, "translationsCreated": {"overall": 23831.0, "change": null}, "learnedWords": {"overall": 13861.0, "change": null}, "readingUsage": {"overall": 1977319.163, "change": null}, "listening": {"overall": 289.71131079105, "change": null}, "lessonImported": {"overall": 604.0, "change": null}, "coinsRead": {"overall": 122595.750559502, "change": null}, "reviewUsage": {"overall": 259203.49, "change": null}, "writing": {"overall": 2455.0, "change": null}, "createdLingQs": {"overall": 24146.0, "change": null}, "knownWords": {"overall": 11755.0, "change": null}, "listeningUsage": {"overall": 247911.522, "change": null}, "translationsUsed": {"overall": 32531.0, "change": null}, "reading": {"overall": 1423794.50561771, "change": null}, "coinsListen": {"overall": 8123.2966054822, "change": null}, "speaking": {"overall": 0.5, "change": null}}